{
  "name": "palette_braille_5_seguisym_fast",
  "templates": [
    {
      "layer": 0,
      "chars": " ",
      "font": "C:/Windows/Fonts/seguisym.ttf",
      "font_size": 24,
      "char_bound_width": 18,
      "char_bound_height": 28,
      "match_method": "fast"
    },
    {
      "layer": 1,
      "chars": "⠁⠂⠃⠄⠅⠆⠇⠈⠉⠊⠋⠌⠍⠎⠏⠐",
      "font": "C:/Windows/Fonts/seguisym.ttf",
      "font_size": 24,
      "char_bound_width": 18,
      "char_bound_height": 28,
      "match_method": "fast"
    },
    {
      "layer": 2,
      "chars": "⠑⠒⠓⠔⠕⠖⠗⠘⠙⠚⠛⠜⠝⠞⠟",
      "font": "C:/Windows/Fonts/seguisym.ttf",
      "font_size": 24,
      "char_bound_width": 18,
      "char_bound_height": 28,
      "match_method": "fast"
    },
    {
      "layer": 3,
      "chars": "⠠⠡⠢⠣⠤⠥⠦⠧⠨⠩⠪⠫⠬⠭⠮⠯",
      "font": "C:/Windows/Fonts/seguisym.ttf",
      "font_size": 24,
      "char_bound_width": 18,
      "char_bound_height": 28,
      "match_method": "fast"
    },
    {
      "layer": 4,
      "chars": "⠰⠱⠲⠳⠴⠵⠶⠷⠸⠹⠺⠻⠼⠽⠾⠿",
      "font": "C:/Windows/Fonts/seguisym.ttf",
      "font_size": 24,
      "char_bound_width": 18,
      "char_bound_height": 28,
      "match_method": "fast"
    }
  ]
}